.DS_Store
HEDM_Platform/HEDM_Platform.py
HEDM_Platform/__init__.py
HEDM_Platform/utilities.py
HEDM_Platform/Demo/Au_ff_demo.npz
HEDM_Platform/Demo/HEXRD_Materials.h5
HEDM_Platform/Demo/RAMS_Materials.h5
HEDM_Platform/Demo/config.yml
HEDM_Platform/Demo/hexrd_Au_detector.yml
HEDM_Platform/Demo/nugget_2_frames_for_test.h5
HEDM_Platform/Demo/nugget_layer0_det0.par
HEDM_Platform/Demo/nugget_layer0_det0_for_test.flt
HEDM_Platform/data/AI_HEDM-Recovered.png
HEDM_Platform/data/AI_HEDM.png
HEDM_Platform/data/HEDM_image.jpg
HEDM_Platform/data/check.jpg
HEDM_Platform/data/ff_HEDM_process.jpg
HEDM_Platform/data/ff_HEDM_process_1.jpg
HEDM_Platform/data/ff_HEDM_process_2.jpg
HEDM_Platform/data/hedm_formats.jpg
HEDM_Platform/data/ilastik.jpg
HEDM_Platform/data/ilastik_a.jpg
HEDM_Platform/data/ilastik_b.jpg
HEDM_Platform/data/image_test.png
HEDM_Platform/data/int_images.jpg
HEDM_Platform/data/nf_hedm_format.jpg
HEDM_Platform/data/stand.jpg
HEDM_Platform/data/sub.jpg
HEDM_Platform/scripts/clean_flt.py
HEDM_Platform/scripts/fitting.py
HEDM_Platform/scripts/gen_flt.py
HEDM_Platform/scripts/indexing.py
HEDM_Platform/scripts/sparse_h5.py
HEDM_Platform-0.4.1.dist-info/METADATA
HEDM_Platform-0.4.1.dist-info/WHEEL
HEDM_Platform-0.4.1.dist-info/entry_points.txt
HEDM_Platform-0.4.1.dist-info/top_level.txt
HEDM_Platform-0.4.1.dist-info/RECORD
