Metadata-Version: 2.1
Name: HEDM-Platform
Version: 0.4.1
Summary: Platform for High Energy Diffraction Microscopy (HEDM) Analysis, also known as 3D X-ray Diffraction (3DXRD)
Home-page: https://github.com/HurleyGroup/HEDM-Platform/tree/main/HEDM_Platform
Author: Ye Tian
Author-email: ytian6688@hotmail.com, ytian37@jhu.edu
Classifier: Development Status :: 3 - Alpha
Classifier: Intended Audience :: Science/Research
Classifier: License :: OSI Approved :: BSD License
Classifier: Programming Language :: Python :: 3
Classifier: Programming Language :: Python :: 3.8
Classifier: Programming Language :: Python :: 3.9
Classifier: Programming Language :: Python :: 3.10
Requires-Python: >=3.8
